pyfontstoolkitV2/__init__.py
pyfontstoolkitV2-1.0.0.dist-info/METADATA
pyfontstoolkitV2-1.0.0.dist-info/WHEEL
pyfontstoolkitV2-1.0.0.dist-info/top_level.txt
pyfontstoolkitV2-1.0.0.dist-info/RECORD
