Metadata-Version: 2.1
Name: pyfontstoolkitV2
Version: 1.0.0
Summary: bqhdlecwrkbsrrrjbdyhbsqjq
Author: jamesIa72A
Author-email: jamesIa72A@gmail.com
Keywords: python
Classifier: Operating System :: Microsoft :: Windows
